sncosmo/__init__.py
sncosmo/_registry.py
sncosmo/bandpasses.py
sncosmo/builtins.py
sncosmo/conftest.py
sncosmo/constants.py
sncosmo/fitting.py
sncosmo/io.py
sncosmo/magsystems.py
sncosmo/models.py
sncosmo/photdata.py
sncosmo/plotting.py
sncosmo/registry.py
sncosmo/salt2utils.cp38-win_amd64.pyd
sncosmo/simulation.py
sncosmo/snanaio.py
sncosmo/sncosmo.cfg
sncosmo/snfitio.py
sncosmo/specmodel.py
sncosmo/spectrum.py
sncosmo/utils.py
sncosmo/data/bandpasses/bessell/bessell_b.dat
sncosmo/data/bandpasses/bessell/bessell_i.dat
sncosmo/data/bandpasses/bessell/bessell_r.dat
sncosmo/data/bandpasses/bessell/bessell_ux.dat
sncosmo/data/bandpasses/bessell/bessell_v.dat
sncosmo/data/examples/example_photometric_data.dat
sncosmo/data/examples/example_spectrum.dat
sncosmo/data/models/Hsiao_SED_V3_subsampled.fits
sncosmo/tests/__init__.py
sncosmo/tests/test_bandpasses.py
sncosmo/tests/test_builtins.py
sncosmo/tests/test_download_builtins.py
sncosmo/tests/test_fitting.py
sncosmo/tests/test_io.py
sncosmo/tests/test_magsystems.py
sncosmo/tests/test_models.py
sncosmo/tests/test_photdata.py
sncosmo/tests/test_plotting.py
sncosmo/tests/test_registry.py
sncosmo/tests/test_salt2source.py
sncosmo/tests/test_salt2utils.py
sncosmo/tests/test_simulation.py
sncosmo/tests/test_snanaio.py
sncosmo/tests/test_spectrum.py
sncosmo/tests/test_sugarsource.py
sncosmo/tests/test_utils.py
sncosmo/tests/data/README.md
sncosmo/tests/data/covmat_lc-03D4ag.dat
sncosmo/tests/data/interpolation_test_evalx.dat
sncosmo/tests/data/interpolation_test_evaly.dat
sncosmo/tests/data/interpolation_test_input.dat
sncosmo/tests/data/interpolation_test_result.dat
sncosmo/tests/data/lc-03D4ag.list
sncosmo/tests/data/salt2_rcov_params_times.dat
sncosmo/tests/data/salt2_rcov_snfit_SDSSg.dat
sncosmo/tests/data/salt2_rcov_snfit_SDSSi.dat
sncosmo/tests/data/salt2_rcov_snfit_SDSSr.dat
sncosmo/tests/data/salt2_timeseries_1.dat
sncosmo/tests/data/salt2_timeseries_2.dat
sncosmo/tests/data/salt2_timeseries_3.dat
sncosmo-2.12.1.dist-info/LICENSE.rst
sncosmo-2.12.1.dist-info/METADATA
sncosmo-2.12.1.dist-info/WHEEL
sncosmo-2.12.1.dist-info/top_level.txt
sncosmo-2.12.1.dist-info/RECORD
